[
  {
    "urn": "144874",
    "name": "Talbot Primary School",
    "address": "Talbot Drive",
    "locality": "Wallisdown",
    "address3": "",
    "town": "Poole",
    "county": "Dorset",
    "postcode": "BH12 5ED",
    "minimum_age": "4",
    "maximum_age": "11",
    "url": "http://www.talbot.poole.sch.uk",
    "phase": "Primary",
    "type": "Academies",
    "detailed_type": "Academy converter"
  },
  {
    "urn": "102607",
    "name": "The Holy Cross School",
    "address": "25 Sandal Road",
    "locality": "",
    "address3": "",
    "town": "New Malden",
    "county": "Surrey",
    "postcode": "KT3 5AR",
    "minimum_age": "11",
    "maximum_age": "18",
    "url": "www.holycross.kingston.sch.uk",
    "phase": "Secondary",
    "type": "Local authority maintained schools",
    "detailed_type": "Voluntary aided school"
  },
  {
    "urn": "123749",
    "name": "Ashlands Church of England First School",
    "address": "North Street",
    "locality": "",
    "address3": "",
    "town": "Crewkerne",
    "county": "Somerset",
    "postcode": "TA18 7AL",
    "minimum_age": "5",
    "maximum_age": "9",
    "url": "www.ashlandsfirstschool.co.uk/",
    "phase": "Primary",
    "type": "Local authority maintained schools",
    "detailed_type": "Voluntary controlled school"
  },
  {
    "urn": "110900",
    "name": "Comberton Village College",
    "address": "West Street",
    "locality": "Comberton",
    "address3": "",
    "town": "Cambridge",
    "county": "Cambridgeshire",
    "postcode": "CB23 7DU",
    "minimum_age": "11",
    "maximum_age": "19",
    "url": "http://www.combertonvc.org",
    "phase": "Secondary",
    "type": "Local authority maintained schools",
    "detailed_type": "Foundation school"
  },
  {
    "urn": "114995",
    "name": "Northlands Primary School and Nursery",
    "address": "Winifred Road",
    "locality": "Pitsea",
    "address3": "",
    "town": "Basildon",
    "county": "Essex",
    "postcode": "SS13 3JQ",
    "minimum_age": "3",
    "maximum_age": "11",
    "url": "www.northlandsprimary.co.uk",
    "phase": "Primary",
    "type": "Local authority maintained schools",
    "detailed_type": "Community school"
  },
  {
    "urn": "106133",
    "name": "Priestnall School",
    "address": "Priestnall Road",
    "locality": "Heaton Mersey",
    "address3": "",
    "town": "Stockport",
    "county": "Cheshire",
    "postcode": "SK4 3HP",
    "minimum_age": "11",
    "maximum_age": "16",
    "url": "www.priestnall.stockport.sch.uk",
    "phase": "Secondary",
    "type": "Local authority maintained schools",
    "detailed_type": "Community school"
  },
  {
    "urn": "124634",
    "name": "Roman Hill Primary School",
    "address": "Avondale Road",
    "locality": "",
    "address3": "",
    "town": "Lowestoft",
    "county": "Suffolk",
    "postcode": "NR32 2NX",
    "minimum_age": "3",
    "maximum_age": "11",
    "url": "www.romanhill-pri.suffolk.sch.uk/",
    "phase": "Primary",
    "type": "Local authority maintained schools",
    "detailed_type": "Community school"
  },
  {
    "urn": "140035",
    "name": "Thomas Hepburn Community Academy",
    "address": "Swards Road",
    "locality": "Felling",
    "address3": "",
    "town": "Gateshead",
    "county": "Tyne and Wear",
    "postcode": "NE10 9UZ",
    "minimum_age": "11",
    "maximum_age": "16",
    "url": "www.thomashepburnacademy.org",
    "phase": "Secondary",
    "type": "Academies",
    "detailed_type": "Academy sponsor led"
  },
  {
    "urn": "121269",
    "name": "Otley Street Community Nursery School",
    "address": "Otley Street",
    "locality": "",
    "address3": "",
    "town": "Skipton",
    "county": "North Yorkshire",
    "postcode": "BD23 1ET",
    "minimum_age": "3",
    "maximum_age": "5",
    "url": "http://www.otleystreet.n-yorks.sch.uk/",
    "phase": "Nursery",
    "type": "Local authority maintained schools",
    "detailed_type": "Local authority nursery school"
  },
  {
    "urn": "133286",
    "name": "Crompton Primary School",
    "address": "Longfield Road",
    "locality": "Shaw",
    "address3": "",
    "town": "Oldham",
    "county": "Greater Manchester",
    "postcode": "OL2 7HD",
    "minimum_age": "3",
    "maximum_age": "11",
    "url": "http://www.crompton.oldham.sch.uk",
    "phase": "Primary",
    "type": "Local authority maintained schools",
    "detailed_type": "Community school"
  },
  {
    "urn": "108796",
    "name": "Eppleton Primary School",
    "address": "Church Road",
    "locality": "Hetton-le-Hole",
    "address3": "",
    "town": "Houghton le Spring",
    "county": "Tyne and Wear",
    "postcode": "DH5 9AJ",
    "minimum_age": "4",
    "maximum_age": "11",
    "url": "",
    "phase": "Primary",
    "type": "Local authority maintained schools",
    "detailed_type": "Community school"
  },
  {
    "urn": "126385",
    "name": "Landford CofE Primary School",
    "address": "Lyndhurst Road",
    "locality": "Landford",
    "address3": "",
    "town": "Salisbury",
    "county": "Wiltshire",
    "postcode": "SP5 2AE",
    "minimum_age": "5",
    "maximum_age": "11",
    "url": "http://www.landford.wilts.sch.uk",
    "phase": "Primary",
    "type": "Local authority maintained schools",
    "detailed_type": "Voluntary aided school"
  },
  {
    "urn": "138025",
    "name": "Monkton Academy",
    "address": "Dame Flora Robson Avenue",
    "locality": "",
    "address3": "",
    "town": "South Shields",
    "county": "Tyne and Wear",
    "postcode": "NE34 9RD",
    "minimum_age": "7",
    "maximum_age": "11",
    "url": "www.monktonacademy.co.uk",
    "phase": "Primary",
    "type": "Academies",
    "detailed_type": "Academy converter"
  },
  {
    "urn": "128255",
    "name": "Park Wood Middle School",
    "address": "Hawk Drive",
    "locality": "",
    "address3": "",
    "town": "Bedford",
    "county": "Bedfordshire",
    "postcode": "MK41 7JE",
    "minimum_age": "9",
    "maximum_age": "13",
    "url": "",
    "phase": "Middle deemed secondary",
    "type": "Local authority maintained schools",
    "detailed_type": "Community school"
  },
  {
    "urn": "113617",
    "name": "Park School",
    "address": "Park Road",
    "locality": "Dartington",
    "address3": "",
    "town": "Totnes",
    "county": "Devon",
    "postcode": "TQ9 6EQ",
    "minimum_age": "3",
    "maximum_age": "11",
    "url": "www.parkschoolonline.com",
    "phase": "Not applicable",
    "type": "Independent schools",
    "detailed_type": "Other independent school"
  },
  {
    "urn": "112417",
    "name": "Hallbankgate Village School",
    "address": "Hallbankgate",
    "locality": "",
    "address3": "",
    "town": "Brampton",
    "county": "Cumbria",
    "postcode": "CA8 2NJ",
    "minimum_age": "3",
    "maximum_age": "11",
    "url": "www.hallbankgate.org.uk/",
    "phase": "Primary",
    "type": "Local authority maintained schools",
    "detailed_type": "Foundation school"
  },
  {
    "urn": "147332",
    "name": "Belvedere Infant School",
    "address": "Mitchell Close",
    "locality": "",
    "address3": "",
    "town": "Belvedere",
    "county": "Kent",
    "postcode": "DA17 6AA",
    "minimum_age": "3",
    "maximum_age": "7",
    "url": "http://www.belvedereinfants.co.uk/",
    "phase": "Primary",
    "type": "Academies",
    "detailed_type": "Academy converter"
  },
  {
    "urn": "112789",
    "name": "Herbert Strutt Primary School",
    "address": "Thornhill Avenue",
    "locality": "",
    "address3": "",
    "town": "Belper",
    "county": "Derbyshire",
    "postcode": "DE56 1SH",
    "minimum_age": "5",
    "maximum_age": "11",
    "url": "http://www.herbertstrutt.derbyshire.sch.uk",
    "phase": "Primary",
    "type": "Local authority maintained schools",
    "detailed_type": "Community school"
  },
  {
    "urn": "110314",
    "name": "Burford School",
    "address": "Marlow Bottom",
    "locality": "",
    "address3": "",
    "town": "Marlow",
    "county": "Buckinghamshire",
    "postcode": "SL7 3PQ",
    "minimum_age": "3",
    "maximum_age": "11",
    "url": "http://www.burfordschool.co.uk",
    "phase": "Primary",
    "type": "Local authority maintained schools",
    "detailed_type": "Community school"
  },
  {
    "urn": "135221",
    "name": "Maple Grove Primary School",
    "address": "St Agnell's Lane",
    "locality": "Grove Hill",
    "address3": "",
    "town": "Hemel Hempstead",
    "county": "Hertfordshire",
    "postcode": "HP2 7BG",
    "minimum_age": "3",
    "maximum_age": "11",
    "url": "www.maplegrove.herts.sch.uk/",
    "phase": "Primary",
    "type": "Local authority maintained schools",
    "detailed_type": "Community school"
  },
  {
    "urn": "141789",
    "name": "Holy Rosary Catholic Primary Academy",
    "address": "Hickman Avenue",
    "locality": "",
    "address3": "",
    "town": "Wolverhampton",
    "county": "West Midlands",
    "postcode": "WV1 2BS",
    "minimum_age": "5",
    "maximum_age": "11",
    "url": "https://www.holyrosaryprimary.co.uk/",
    "phase": "Primary",
    "type": "Academies",
    "detailed_type": "Academy converter"
  },
  {
    "urn": "119196",
    "name": "Ramsbottom Stubbins Primary School",
    "address": "Bolton Road North",
    "locality": "Stubbins",
    "address3": "Ramsbottom",
    "town": "Bury",
    "county": "Lancashire",
    "postcode": "BL0 0NA",
    "minimum_age": "4",
    "maximum_age": "11",
    "url": "www.stubbins.lancs.sch.uk",
    "phase": "Primary",
    "type": "Local authority maintained schools",
    "detailed_type": "Community school"
  },
  {
    "urn": "128600",
    "name": "Ambleside CofE Infant School",
    "address": "Vicarage Road",
    "locality": "",
    "address3": "",
    "town": "Ambleside",
    "county": "Cumbria",
    "postcode": "LA22 9DH",
    "minimum_age": "4",
    "maximum_age": "7",
    "url": "",
    "phase": "Primary",
    "type": "Local authority maintained schools",
    "detailed_type": "Voluntary aided school"
  },
  {
    "urn": "104352",
    "name": "Grove Primary School",
    "address": "Caledonia Road",
    "locality": "",
    "address3": "",
    "town": "Wolverhampton",
    "county": "West Midlands",
    "postcode": "WV2 1HZ",
    "minimum_age": "3",
    "maximum_age": "11",
    "url": "www.groveprimaryschool.co.uk",
    "phase": "Primary",
    "type": "Local authority maintained schools",
    "detailed_type": "Community school"
  },
  {
    "urn": "145315",
    "name": "The Halley Academy",
    "address": "Corelli Road",
    "locality": "",
    "address3": "",
    "town": "London",
    "county": "",
    "postcode": "SE3 8EP",
    "minimum_age": "11",
    "maximum_age": "19",
    "url": "www.thehalleyacademy.org.uk",
    "phase": "Secondary",
    "type": "Academies",
    "detailed_type": "Academy sponsor led"
  },
  {
    "urn": "143840",
    "name": "Queensgate College",
    "address": "Morningside Centre",
    "locality": "Cresset Road",
    "address3": "",
    "town": "London",
    "county": "",
    "postcode": "E9 6SJ",
    "minimum_age": "11",
    "maximum_age": "16",
    "url": "www.queensgatecollege.co.uk",
    "phase": "Not applicable",
    "type": "Independent schools",
    "detailed_type": "Other independent school"
  },
  {
    "urn": "140302",
    "name": "Westlea Primary School",
    "address": "Langstone Way",
    "locality": "Westlea Down",
    "address3": "",
    "town": "Swindon",
    "county": "Wiltshire",
    "postcode": "SN5 7BT",
    "minimum_age": "4",
    "maximum_age": "11",
    "url": "www.westleaprimary.co.uk/",
    "phase": "Primary",
    "type": "Academies",
    "detailed_type": "Academy converter"
  },
  {
    "urn": "123384",
    "name": "Newport Infant School",
    "address": "Granville Avenue",
    "locality": "",
    "address3": "",
    "town": "Newport",
    "county": "Shropshire",
    "postcode": "TF10 7DX",
    "minimum_age": "5",
    "maximum_age": "7",
    "url": "www.newportinfants.taw.org.uk/",
    "phase": "Primary",
    "type": "Local authority maintained schools",
    "detailed_type": "Community school"
  },
  {
    "urn": "120322",
    "name": "Oakham School",
    "address": "Chapel Close",
    "locality": "",
    "address3": "",
    "town": "Oakham",
    "county": "Rutland",
    "postcode": "LE15 6DT",
    "minimum_age": "9",
    "maximum_age": "18",
    "url": "www.oakham.rutland.sch.uk",
    "phase": "Not applicable",
    "type": "Independent schools",
    "detailed_type": "Other independent school"
  },
  {
    "urn": "102660",
    "name": "Stanford Primary School",
    "address": "Chilmark Road",
    "locality": "Norbury",
    "address3": "",
    "town": "London",
    "county": "",
    "postcode": "SW16 5HB",
    "minimum_age": "3",
    "maximum_age": "11",
    "url": "www.stanford.merton.sch.uk",
    "phase": "Primary",
    "type": "Local authority maintained schools",
    "detailed_type": "Community school"
  },
  {
    "urn": "113975",
    "name": "Seaham Harbour Nursery School",
    "address": "Bottleworks Road",
    "locality": "Seaham Harbour",
    "address3": "",
    "town": "Seaham",
    "county": "County Durham",
    "postcode": "SR7 7NN",
    "minimum_age": "2",
    "maximum_age": "5",
    "url": "www.seahamharbour.durham.sch.uk",
    "phase": "Nursery",
    "type": "Local authority maintained schools",
    "detailed_type": "Local authority nursery school"
  },
  {
    "urn": "139612",
    "name": "The Ferrars Academy",
    "address": "Macaulay Road",
    "locality": "",
    "address3": "",
    "town": "Luton",
    "county": "Bedfordshire",
    "postcode": "LU4 0LL",
    "minimum_age": "3",
    "maximum_age": "7",
    "url": "www.theferrarsacademy.co.uk/",
    "phase": "Primary",
    "type": "Academies",
    "detailed_type": "Academy converter"
  },
  {
    "urn": "136790",
    "name": "Fosse Way Academy",
    "address": "Ash Grove",
    "locality": "North Hykeham",
    "address3": "",
    "town": "Lincoln",
    "county": "Lincolnshire",
    "postcode": "LN6 8DU",
    "minimum_age": "3",
    "maximum_age": "11",
    "url": "www.fosse-way-academy.org",
    "phase": "Primary",
    "type": "Academies",
    "detailed_type": "Academy converter"
  },
  {
    "urn": "147030",
    "name": "Heath House Hospital School",
    "address": "Priory Hospital Bristol",
    "locality": "Heath House Lane",
    "address3": "Stapleton",
    "town": "Bristol",
    "county": "",
    "postcode": "BS16 1EQ",
    "minimum_age": "11",
    "maximum_age": "18",
    "url": "",
    "phase": "Not applicable",
    "type": "Independent schools",
    "detailed_type": "Other independent school"
  },
  {
    "urn": "133725",
    "name": "Jarrow School",
    "address": "Field Terrace",
    "locality": "",
    "address3": "",
    "town": "Jarrow",
    "county": "Tyne and Wear",
    "postcode": "NE32 5PR",
    "minimum_age": "11",
    "maximum_age": "16",
    "url": "http://www.jarrowschool.com/",
    "phase": "Secondary",
    "type": "Local authority maintained schools",
    "detailed_type": "Foundation school"
  },
  {
    "urn": "127555",
    "name": "Gidlow Middle School",
    "address": "Buckley Street West",
    "locality": "",
    "address3": "",
    "town": "Wigan",
    "county": "Lancashire",
    "postcode": "WN6 7PQ",
    "minimum_age": "10",
    "maximum_age": "13",
    "url": "",
    "phase": "Middle deemed secondary",
    "type": "Local authority maintained schools",
    "detailed_type": "Community school"
  },
  {
    "urn": "113560",
    "name": "Uffculme School",
    "address": "Chapel Hill",
    "locality": "Uffculme",
    "address3": "",
    "town": "Cullompton",
    "county": "Devon",
    "postcode": "EX15 3AG",
    "minimum_age": "11",
    "maximum_age": "16",
    "url": "http://www.uffculme.devon.sch.uk/index.html",
    "phase": "Secondary",
    "type": "Local authority maintained schools",
    "detailed_type": "Foundation school"
  },
  {
    "urn": "124805",
    "name": "Great Cornard Middle School",
    "address": "Wells Hall Road",
    "locality": "Great Cornard",
    "address3": "",
    "town": "Sudbury",
    "county": "Suffolk",
    "postcode": "CO10 0NH",
    "minimum_age": "9",
    "maximum_age": "13",
    "url": "http://gcms.learn-together.org",
    "phase": "Middle deemed secondary",
    "type": "Local authority maintained schools",
    "detailed_type": "Community school"
  },
  {
    "urn": "101187",
    "name": "Dorothy Barley Junior School and Special Needs Base (MLD)",
    "address": "Ivinghoe Road",
    "locality": "",
    "address3": "",
    "town": "Dagenham",
    "county": "Essex",
    "postcode": "RM8 2NB",
    "minimum_age": "7",
    "maximum_age": "11",
    "url": "http://www.d-barley-j.bardaglea.org.uk/",
    "phase": "Primary",
    "type": "Local authority maintained schools",
    "detailed_type": "Community school"
  },
  {
    "urn": "118882",
    "name": "Aylesford School",
    "address": "Teapot Lane",
    "locality": "",
    "address3": "",
    "town": "Aylesford",
    "county": "Kent",
    "postcode": "ME20 7JU",
    "minimum_age": "11",
    "maximum_age": "18",
    "url": "http://www.aylesford.kent.sch.uk/",
    "phase": "Secondary",
    "type": "Local authority maintained schools",
    "detailed_type": "Foundation school"
  },
  {
    "urn": "125111",
    "name": "Saxon Primary School",
    "address": "Briar Road",
    "locality": "",
    "address3": "",
    "town": "Shepperton",
    "county": "Surrey",
    "postcode": "TW17 0JB",
    "minimum_age": "4",
    "maximum_age": "11",
    "url": "www.saxon.surrey.sch.uk",
    "phase": "Primary",
    "type": "Local authority maintained schools",
    "detailed_type": "Community school"
  },
  {
    "urn": "105782",
    "name": "Sparrow Hill Primary and Community School",
    "address": "Sparrow Hill",
    "locality": "",
    "address3": "",
    "town": "Rochdale",
    "county": "Lancashire",
    "postcode": "OL16 1QT",
    "minimum_age": "3",
    "maximum_age": "11",
    "url": "http://www.sparrowhill.rochdale.sch.uk/",
    "phase": "Primary",
    "type": "Local authority maintained schools",
    "detailed_type": "Community school"
  },
  {
    "urn": "122590",
    "name": "Bowbridge Junior School",
    "address": "Bailey Road",
    "locality": "",
    "address3": "",
    "town": "Newark",
    "county": "Nottinghamshire",
    "postcode": "NG24 4EP",
    "minimum_age": "7",
    "maximum_age": "11",
    "url": "",
    "phase": "Primary",
    "type": "Local authority maintained schools",
    "detailed_type": "Community school"
  },
  {
    "urn": "100990",
    "name": "Balham Nursery School",
    "address": "72 Endlesham Road",
    "locality": "Balham",
    "address3": "",
    "town": "London",
    "county": "",
    "postcode": "SW12 8JL",
    "minimum_age": "2",
    "maximum_age": "5",
    "url": "www.balham-nursery.wandsworth.sch.uk",
    "phase": "Nursery",
    "type": "Local authority maintained schools",
    "detailed_type": "Local authority nursery school"
  },
  {
    "urn": "140187",
    "name": "Benedict Primary School",
    "address": "Church Road",
    "locality": "",
    "address3": "",
    "town": "Mitcham",
    "county": "Surrey",
    "postcode": "CR4 3BE",
    "minimum_age": "3",
    "maximum_age": "11",
    "url": "www.benedictprimaryschool.org.uk/",
    "phase": "Primary",
    "type": "Academies",
    "detailed_type": "Academy sponsor led"
  },
  {
    "urn": "129513",
    "name": "Woodville Residential Special School",
    "address": "Ribchester Road",
    "locality": "Longridge",
    "address3": "",
    "town": "Preston",
    "county": "Lancashire",
    "postcode": "PR3 3XB",
    "minimum_age": "8",
    "maximum_age": "12",
    "url": "",
    "phase": "Not applicable",
    "type": "Special schools",
    "detailed_type": "Community special school"
  },
  {
    "urn": "117773",
    "name": "Endike Primary School",
    "address": "Endike Lane",
    "locality": "",
    "address3": "",
    "town": "Hull",
    "county": "",
    "postcode": "HU6 7UR",
    "minimum_age": "3",
    "maximum_age": "11",
    "url": "http://www.endike.hull.sch.uk",
    "phase": "Primary",
    "type": "Local authority maintained schools",
    "detailed_type": "Community school"
  },
  {
    "urn": "115339",
    "name": "Westcliff High School for Girls",
    "address": "Kenilworth Gardens",
    "locality": "",
    "address3": "",
    "town": "Westcliff-on-Sea",
    "county": "Essex",
    "postcode": "SS0 0BS",
    "minimum_age": "11",
    "maximum_age": "18",
    "url": "http://www.whsg.info",
    "phase": "Secondary",
    "type": "Local authority maintained schools",
    "detailed_type": "Foundation school"
  },
  {
    "urn": "127364",
    "name": "Lydiate Infant School",
    "address": "Lambshear Lane",
    "locality": "Lydiate",
    "address3": "",
    "town": "Liverpool",
    "county": "Merseyside",
    "postcode": "L31 2JZ",
    "minimum_age": "4",
    "maximum_age": "7",
    "url": "",
    "phase": "Primary",
    "type": "Local authority maintained schools",
    "detailed_type": "Community school"
  },
  {
    "urn": "127048",
    "name": "Calshot Infant School",
    "address": "Calshot Road",
    "locality": "",
    "address3": "",
    "town": "Birmingham",
    "county": "West Midlands",
    "postcode": "B42 2BY",
    "minimum_age": "4",
    "maximum_age": "7",
    "url": "",
    "phase": "Primary",
    "type": "Local authority maintained schools",
    "detailed_type": "Community school"
  },
  {
    "urn": "112545",
    "name": "Renishaw Primary School",
    "address": "Hague Lane",
    "locality": "Renishaw",
    "address3": "",
    "town": "Sheffield",
    "county": "Derbyshire",
    "postcode": "S21 3UR",
    "minimum_age": "3",
    "maximum_age": "11",
    "url": "www.renishawprimary.org.uk",
    "phase": "Primary",
    "type": "Local authority maintained schools",
    "detailed_type": "Community school"
  },
  {
    "urn": "121555",
    "name": "Burton Leonard Church of England Primary School",
    "address": "Burton Leonard",
    "locality": "",
    "address3": "",
    "town": "Harrogate",
    "county": "North Yorkshire",
    "postcode": "HG3 3RW",
    "minimum_age": "5",
    "maximum_age": "11",
    "url": "www.burtonleonard.n-yorks.sch.uk",
    "phase": "Primary",
    "type": "Local authority maintained schools",
    "detailed_type": "Voluntary controlled school"
  },
  {
    "urn": "137573",
    "name": "Fearon Cottage",
    "address": "Boreley Lane",
    "locality": "",
    "address3": "",
    "town": "Worcester",
    "county": "Worcestershire",
    "postcode": "WR9 0HW",
    "minimum_age": "9",
    "maximum_age": "19",
    "url": "",
    "phase": "Not applicable",
    "type": "Special schools",
    "detailed_type": "Other independent special school"
  },
  {
    "urn": "135975",
    "name": "Ashlea House School",
    "address": "Ashlea House",
    "locality": "474 Stockport Road",
    "address3": "Denton",
    "town": "Manchester",
    "county": "Greater Manchester",
    "postcode": "M34 6ET",
    "minimum_age": "11",
    "maximum_age": "18",
    "url": "www.fullcirclecare.co.uk",
    "phase": "Not applicable",
    "type": "Independent schools",
    "detailed_type": "Other independent school"
  },
  {
    "urn": "147928",
    "name": "St Godrics Catholic Primary School, Thornley",
    "address": "Thornley Road",
    "locality": "Wheatley Hill",
    "address3": "",
    "town": "Durham",
    "county": "",
    "postcode": "DH6 3NR",
    "minimum_age": "4",
    "maximum_age": "11",
    "url": "http://atschool.eduweb.co.uk/thornleyrc.durham/",
    "phase": "Primary",
    "type": "Academies",
    "detailed_type": "Academy converter"
  },
  {
    "urn": "140922",
    "name": "Idsall School",
    "address": "Coppice Green Lane",
    "locality": "",
    "address3": "",
    "town": "Shifnal",
    "county": "Shropshire",
    "postcode": "TF11 8PD",
    "minimum_age": "11",
    "maximum_age": "18",
    "url": "http://www.idsallschool.org/",
    "phase": "Secondary",
    "type": "Academies",
    "detailed_type": "Academy converter"
  },
  {
    "urn": "103959",
    "name": "Tividale Community Primary School",
    "address": "Dudley Road West",
    "locality": "Tividale",
    "address3": "",
    "town": "Oldbury",
    "county": "West Midlands",
    "postcode": "B69 2HT",
    "minimum_age": "3",
    "maximum_age": "11",
    "url": "",
    "phase": "Primary",
    "type": "Local authority maintained schools",
    "detailed_type": "Community school"
  },
  {
    "urn": "126547",
    "name": "St Luke's School",
    "address": "Cricklade Road",
    "locality": "",
    "address3": "",
    "town": "Swindon",
    "county": "Wiltshire",
    "postcode": "SN2 7AS",
    "minimum_age": "11",
    "maximum_age": "16",
    "url": "",
    "phase": "Not applicable",
    "type": "Special schools",
    "detailed_type": "Community special school"
  },
  {
    "urn": "146368",
    "name": "Van Gogh Primary",
    "address": "Cowley Road",
    "locality": "",
    "address3": "",
    "town": "London",
    "county": "",
    "postcode": "SW9 6HF",
    "minimum_age": "3",
    "maximum_age": "11",
    "url": "www.vangoghprimary.org.uk",
    "phase": "Primary",
    "type": "Academies",
    "detailed_type": "Academy converter"
  },
  {
    "urn": "100216",
    "name": "Amherst Primary School",
    "address": "Sigdon Road",
    "locality": "Hackney",
    "address3": "",
    "town": "London",
    "county": "",
    "postcode": "E8 1AS",
    "minimum_age": "3",
    "maximum_age": "11",
    "url": "",
    "phase": "Primary",
    "type": "Local authority maintained schools",
    "detailed_type": "Community school"
  },
  {
    "urn": "100961",
    "name": "St Saviour's Church of England Primary School",
    "address": "Chrisp Street",
    "locality": "Poplar",
    "address3": "",
    "town": "London",
    "county": "",
    "postcode": "E14 6BB",
    "minimum_age": "3",
    "maximum_age": "11",
    "url": "www.stsavioursschool.org.uk",
    "phase": "Primary",
    "type": "Local authority maintained schools",
    "detailed_type": "Voluntary aided school"
  },
  {
    "urn": "104918",
    "name": "St Patrick's Catholic Primary School",
    "address": "Radnor Drive",
    "locality": "Churchtown",
    "address3": "",
    "town": "Southport",
    "county": "Lancashire",
    "postcode": "PR9 9RR",
    "minimum_age": "5",
    "maximum_age": "11",
    "url": "http://www.stpatrickschurchtown.com",
    "phase": "Primary",
    "type": "Local authority maintained schools",
    "detailed_type": "Voluntary aided school"
  },
  {
    "urn": "129529",
    "name": "Herrick County Junior School",
    "address": "Lockerbie Avenue",
    "locality": "",
    "address3": "",
    "town": "Leicester",
    "county": "Leicestershire",
    "postcode": "LE4 7NJ",
    "minimum_age": "7",
    "maximum_age": "11",
    "url": "",
    "phase": "Primary",
    "type": "Local authority maintained schools",
    "detailed_type": "Community school"
  },
  {
    "urn": "146165",
    "name": "High Wycombe Hospital School",
    "address": "309 Cressex Road",
    "locality": "",
    "address3": "",
    "town": "High Wycombe",
    "county": "Buckinghamshire",
    "postcode": "HP12 4QF",
    "minimum_age": "13",
    "maximum_age": "18",
    "url": "",
    "phase": "Not applicable",
    "type": "Special schools",
    "detailed_type": "Other independent special school"
  },
  {
    "urn": "110420",
    "name": "Stone Church of England Combined School",
    "address": "Oxford Road",
    "locality": "",
    "address3": "",
    "town": "Aylesbury",
    "county": "",
    "postcode": "HP17 8PD",
    "minimum_age": "4",
    "maximum_age": "11",
    "url": "www.stone.bucks.sch.uk",
    "phase": "Primary",
    "type": "Local authority maintained schools",
    "detailed_type": "Voluntary controlled school"
  },
  {
    "urn": "121336",
    "name": "Scarborough, Overdale Community Primary School",
    "address": "Hawthorn Walk",
    "locality": "Eastfield",
    "address3": "",
    "town": "Scarborough",
    "county": "North Yorkshire",
    "postcode": "YO11 3HW",
    "minimum_age": "3",
    "maximum_age": "11",
    "url": "http://overdale.n-yorks.sch.uk/",
    "phase": "Primary",
    "type": "Local authority maintained schools",
    "detailed_type": "Community school"
  },
  {
    "urn": "111891",
    "name": "Treverbyn Community Primary School",
    "address": "Stenalees",
    "locality": "",
    "address3": "",
    "town": "St Austell",
    "county": "Cornwall",
    "postcode": "PL26 8TL",
    "minimum_age": "4",
    "maximum_age": "11",
    "url": "",
    "phase": "Primary",
    "type": "Local authority maintained schools",
    "detailed_type": "Community school"
  },
  {
    "urn": "100757",
    "name": "Sydenham High School GDST",
    "address": "19 Westwood Hill",
    "locality": "",
    "address3": "",
    "town": "London",
    "county": "",
    "postcode": "SE26 6BL",
    "minimum_age": "4",
    "maximum_age": "18",
    "url": "https://www.sydenhamhighschool.gdst.net/",
    "phase": "Not applicable",
    "type": "Independent schools",
    "detailed_type": "Other independent school"
  },
  {
    "urn": "111572",
    "name": "Beechwood Infant School",
    "address": "Beechwood Avenue",
    "locality": "",
    "address3": "",
    "town": "Middlesbrough",
    "county": "",
    "postcode": "TS4 3AP",
    "minimum_age": "3",
    "maximum_age": "7",
    "url": "http://www.millenniumschools.co.uk/pub/middlesbrough/beechwood-inf/a.html",
    "phase": "Primary",
    "type": "Local authority maintained schools",
    "detailed_type": "Community school"
  },
  {
    "urn": "130877",
    "name": "St Andrew's Benn CofE (Voluntary Aided) Primary School",
    "address": "Chester Street",
    "locality": "",
    "address3": "",
    "town": "Rugby",
    "county": "Warwickshire",
    "postcode": "CV21 3NX",
    "minimum_age": "3",
    "maximum_age": "11",
    "url": "www.standrewsbennprimary.co.uk/",
    "phase": "Primary",
    "type": "Local authority maintained schools",
    "detailed_type": "Voluntary aided school"
  },
  {
    "urn": "117110",
    "name": "South Hill Primary School",
    "address": "Heath Lane",
    "locality": "",
    "address3": "",
    "town": "Hemel Hempstead",
    "county": "Hertfordshire",
    "postcode": "HP1 1TT",
    "minimum_age": "5",
    "maximum_age": "11",
    "url": "http://www.southhill.herts.sch.uk",
    "phase": "Primary",
    "type": "Local authority maintained schools",
    "detailed_type": "Community school"
  },
  {
    "urn": "104486",
    "name": "Higher Side Community Comprehensive School",
    "address": "Cumber Lane",
    "locality": "Whiston",
    "address3": "",
    "town": "Prescot",
    "county": "Merseyside",
    "postcode": "L35 2XG",
    "minimum_age": "11",
    "maximum_age": "16",
    "url": "http://www.higherside.knowsley.sch.uk/default.asp",
    "phase": "Secondary",
    "type": "Local authority maintained schools",
    "detailed_type": "Community school"
  },
  {
    "urn": "137667",
    "name": "Kesteven and Sleaford High School Selective Academy",
    "address": "Jermyn Street",
    "locality": "",
    "address3": "",
    "town": "Sleaford",
    "county": "Lincolnshire",
    "postcode": "NG34 7RS",
    "minimum_age": "11",
    "maximum_age": "18",
    "url": "www.kshs.uk",
    "phase": "Secondary",
    "type": "Academies",
    "detailed_type": "Academy converter"
  },
  {
    "urn": "145790",
    "name": "St Peter's CofE Primary School",
    "address": "Shrubbery Gardens",
    "locality": "Wem",
    "address3": "",
    "town": "Shrewsbury",
    "county": "Shropshire",
    "postcode": "SY4 5BX",
    "minimum_age": "3",
    "maximum_age": "11",
    "url": "http://www.st-petersprimaryschool.co.uk/",
    "phase": "Primary",
    "type": "Academies",
    "detailed_type": "Academy converter"
  },
  {
    "urn": "122488",
    "name": "Healdswood Infants' and Nursery School",
    "address": "Barker Avenue",
    "locality": "Skegby",
    "address3": "",
    "town": "Sutton-in-Ashfield",
    "county": "Nottinghamshire",
    "postcode": "NG17 3FQ",
    "minimum_age": "3",
    "maximum_age": "7",
    "url": "www.healdswood.notts.sch.uk/",
    "phase": "Primary",
    "type": "Local authority maintained schools",
    "detailed_type": "Community school"
  },
  {
    "urn": "103376",
    "name": "Twickenham Primary School",
    "address": "Twickenham Road",
    "locality": "Kingstanding",
    "address3": "",
    "town": "Birmingham",
    "county": "West Midlands",
    "postcode": "B44 0NR",
    "minimum_age": "3",
    "maximum_age": "11",
    "url": "http://www.twickenham.bham.sch.uk",
    "phase": "Primary",
    "type": "Local authority maintained schools",
    "detailed_type": "Community school"
  },
  {
    "urn": "119726",
    "name": "Bowland High",
    "address": "Riversmead",
    "locality": "Grindleton",
    "address3": "",
    "town": "Clitheroe",
    "county": "Lancashire",
    "postcode": "BB7 4QS",
    "minimum_age": "11",
    "maximum_age": "16",
    "url": "",
    "phase": "Secondary",
    "type": "Local authority maintained schools",
    "detailed_type": "Community school"
  },
  {
    "urn": "144599",
    "name": "Southgate Primary",
    "address": "Barrington Road",
    "locality": "Southgate",
    "address3": "",
    "town": "Crawley",
    "county": "West Sussex",
    "postcode": "RH10 6DG",
    "minimum_age": "4",
    "maximum_age": "11",
    "url": "www.southgateprimary.co.uk",
    "phase": "Primary",
    "type": "Academies",
    "detailed_type": "Academy sponsor led"
  },
  {
    "urn": "130944",
    "name": "Westminster Primary School",
    "address": "Stamford Road",
    "locality": "Handsworth",
    "address3": "",
    "town": "Birmingham",
    "county": "West Midlands",
    "postcode": "B20 3PN",
    "minimum_age": "3",
    "maximum_age": "11",
    "url": "www.westmnst.bham.sch.uk",
    "phase": "Primary",
    "type": "Local authority maintained schools",
    "detailed_type": "Community school"
  },
  {
    "urn": "131580",
    "name": "Beacon Primary School",
    "address": "Davis Road",
    "locality": "New Invention",
    "address3": "",
    "town": "Willenhall",
    "county": "West Midlands",
    "postcode": "WV12 5HA",
    "minimum_age": "2",
    "maximum_age": "11",
    "url": "www.beaconprimaryschool.co.uk/",
    "phase": "Primary",
    "type": "Local authority maintained schools",
    "detailed_type": "Community school"
  },
  {
    "urn": "127180",
    "name": "Kingshurst School",
    "address": "Cooks Lane",
    "locality": "Kingshurst",
    "address3": "",
    "town": "Birmingham",
    "county": "West Midlands",
    "postcode": "B37 6NU",
    "minimum_age": "11",
    "maximum_age": "16",
    "url": "",
    "phase": "Secondary",
    "type": "Local authority maintained schools",
    "detailed_type": "Community school"
  },
  {
    "urn": "108161",
    "name": "Moorthorpe First School",
    "address": "Regent Street",
    "locality": "South Elmsall",
    "address3": "",
    "town": "Pontefract",
    "county": "West Yorkshire",
    "postcode": "WF9 2BL",
    "minimum_age": "5",
    "maximum_age": "9",
    "url": "",
    "phase": "Primary",
    "type": "Local authority maintained schools",
    "detailed_type": "Community school"
  },
  {
    "urn": "120897",
    "name": "Queensway Infant School and Nursery, Thetford",
    "address": "Queensway",
    "locality": "",
    "address3": "",
    "town": "Thetford",
    "county": "Norfolk",
    "postcode": "IP24 3DR",
    "minimum_age": "3",
    "maximum_age": "7",
    "url": "www.queensway-inf.norfolk.sch.uk",
    "phase": "Primary",
    "type": "Local authority maintained schools",
    "detailed_type": "Community school"
  },
  {
    "urn": "136477",
    "name": "West Grantham Academy The Earl of Dysart",
    "address": "Dysart Road",
    "locality": "",
    "address3": "",
    "town": "Grantham",
    "county": "Lincolnshire",
    "postcode": "NG31 7LP",
    "minimum_age": "4",
    "maximum_age": "11",
    "url": "www.wgacademiestrust.org.uk",
    "phase": "Primary",
    "type": "Academies",
    "detailed_type": "Academy converter"
  },
  {
    "urn": "136158",
    "name": "The Nuneaton Academy",
    "address": "Radnor Drive",
    "locality": "",
    "address3": "",
    "town": "Nuneaton",
    "county": "Warwickshire",
    "postcode": "CV10 7PD",
    "minimum_age": "11",
    "maximum_age": "16",
    "url": "http://www.nuneatonacademy.co.uk/",
    "phase": "Secondary",
    "type": "Academies",
    "detailed_type": "Academy sponsor led"
  },
  {
    "urn": "111464",
    "name": "Fallibroome High School",
    "address": "Priory Lane",
    "locality": "Upton",
    "address3": "",
    "town": "Macclesfield",
    "county": "Cheshire",
    "postcode": "SK10 4AF",
    "minimum_age": "11",
    "maximum_age": "18",
    "url": "http://www.fallibroome.cheshire.sch.uk/",
    "phase": "Secondary",
    "type": "Local authority maintained schools",
    "detailed_type": "Foundation school"
  },
  {
    "urn": "120488",
    "name": "Wragby Primary School",
    "address": "Silver Street",
    "locality": "Wragby",
    "address3": "",
    "town": "Market Rasen",
    "county": "Lincolnshire",
    "postcode": "LN8 5PJ",
    "minimum_age": "4",
    "maximum_age": "11",
    "url": "http://www.wragby.lincs.sch.uk",
    "phase": "Primary",
    "type": "Local authority maintained schools",
    "detailed_type": "Community school"
  },
  {
    "urn": "120951",
    "name": "Tuckswood First School",
    "address": "Allanadale Road",
    "locality": "Tuckswood",
    "address3": "",
    "town": "Norwich",
    "county": "Norfolk",
    "postcode": "NR4 6BP",
    "minimum_age": "5",
    "maximum_age": "8",
    "url": "http://www.tuckswoodfirst.norfolk.sch.uk/",
    "phase": "Primary",
    "type": "Local authority maintained schools",
    "detailed_type": "Community school"
  },
  {
    "urn": "116795",
    "name": "Clehonger CofE Primary School",
    "address": "Gosmore Road",
    "locality": "Clehonger",
    "address3": "",
    "town": "Hereford",
    "county": "Herefordshire",
    "postcode": "HR2 9SN",
    "minimum_age": "5",
    "maximum_age": "11",
    "url": "www.clehongerschool.co.uk",
    "phase": "Primary",
    "type": "Local authority maintained schools",
    "detailed_type": "Voluntary controlled school"
  },
  {
    "urn": "138164",
    "name": "St Thomas More's Catholic Primary School, Colchester",
    "address": "Priory Street",
    "locality": "",
    "address3": "",
    "town": "Colchester",
    "county": "Essex",
    "postcode": "CO1 2QB",
    "minimum_age": "4",
    "maximum_age": "11",
    "url": "www.stthomasmores.co.uk",
    "phase": "Primary",
    "type": "Academies",
    "detailed_type": "Academy converter"
  },
  {
    "urn": "120162",
    "name": "Swannington Church of England Primary School",
    "address": "Main Street",
    "locality": "Swannington",
    "address3": "",
    "town": "Coalville",
    "county": "Leicestershire",
    "postcode": "LE67 8QJ",
    "minimum_age": "4",
    "maximum_age": "11",
    "url": "http://www.swann.leics.sch.uk/",
    "phase": "Primary",
    "type": "Local authority maintained schools",
    "detailed_type": "Voluntary controlled school"
  },
  {
    "urn": "141263",
    "name": "Robsack Wood Primary Academy",
    "address": "Whatlington Way",
    "locality": "",
    "address3": "",
    "town": "St Leonards-on-Sea",
    "county": "East Sussex",
    "postcode": "TN38 9TE",
    "minimum_age": "3",
    "maximum_age": "11",
    "url": "http://www.robsackwoodprimaryacademy.org.uk/",
    "phase": "Primary",
    "type": "Academies",
    "detailed_type": "Academy converter"
  },
  {
    "urn": "111212",
    "name": "Winnington Park Community Primary and Nursery School",
    "address": "Firdale Road",
    "locality": "Firdale Park",
    "address3": "Winnington",
    "town": "Northwich",
    "county": "Cheshire",
    "postcode": "CW8 4AZ",
    "minimum_age": "3",
    "maximum_age": "11",
    "url": "www.winningtonpark.cheshire.sch.uk/",
    "phase": "Primary",
    "type": "Local authority maintained schools",
    "detailed_type": "Community school"
  },
  {
    "urn": "123609",
    "name": "The Old Hall School",
    "address": "Stanley Road",
    "locality": "Wellington",
    "address3": "",
    "town": "Telford",
    "county": "Shropshire",
    "postcode": "TF1 3LB",
    "minimum_age": "4",
    "maximum_age": "11",
    "url": "www.oldhall.co.uk",
    "phase": "Not applicable",
    "type": "Independent schools",
    "detailed_type": "Other independent school"
  },
  {
    "urn": "127947",
    "name": "Brodetsky First School",
    "address": "Wentworth Avenue",
    "locality": "",
    "address3": "",
    "town": "Leeds",
    "county": "West Yorkshire",
    "postcode": "LS17 7TN",
    "minimum_age": "5",
    "maximum_age": "9",
    "url": "",
    "phase": "Primary",
    "type": "Local authority maintained schools",
    "detailed_type": "Voluntary aided school"
  },
  {
    "urn": "102883",
    "name": "Carlisle Infant School",
    "address": "Broad Lane",
    "locality": "",
    "address3": "",
    "town": "Hampton",
    "county": "",
    "postcode": "TW12 3AJ",
    "minimum_age": "5",
    "maximum_age": "7",
    "url": "www.carlisleandhamptonhillfed.richmond.sch.uk",
    "phase": "Primary",
    "type": "Local authority maintained schools",
    "detailed_type": "Community school"
  },
  {
    "urn": "120617",
    "name": "The Saint Hugh's Catholic Primary School, Lincoln",
    "address": "Woodfield Avenue",
    "locality": "Doddington Park",
    "address3": "",
    "town": "Lincoln",
    "county": "Lincolnshire",
    "postcode": "LN6 0SH",
    "minimum_age": "5",
    "maximum_age": "11",
    "url": "http://www.st-hughs-school.org.uk",
    "phase": "Primary",
    "type": "Local authority maintained schools",
    "detailed_type": "Voluntary aided school"
  },
  {
    "urn": "138392",
    "name": "Glenleigh Park Primary Academy",
    "address": "Gunters Lane",
    "locality": "",
    "address3": "",
    "town": "Bexhill-on-Sea",
    "county": "East Sussex",
    "postcode": "TN39 4ED",
    "minimum_age": "2",
    "maximum_age": "11",
    "url": "www.glenleighparkprimaryacademy.mosaicaeducation.com/",
    "phase": "Primary",
    "type": "Academies",
    "detailed_type": "Academy sponsor led"
  },
  {
    "urn": "138667",
    "name": "Lord Williams's School",
    "address": "Oxford Road",
    "locality": "",
    "address3": "",
    "town": "Thame",
    "county": "Oxfordshire",
    "postcode": "OX9 2AQ",
    "minimum_age": "11",
    "maximum_age": "18",
    "url": "http://www.lordwilliams.oxon.sch.uk",
    "phase": "Secondary",
    "type": "Academies",
    "detailed_type": "Academy converter"
  },
  {
    "urn": "127926",
    "name": "Meanwood CofE First School",
    "address": "Green Road",
    "locality": "",
    "address3": "",
    "town": "Leeds",
    "county": "West Yorkshire",
    "postcode": "LS6 4LD",
    "minimum_age": "5",
    "maximum_age": "9",
    "url": "",
    "phase": "Primary",
    "type": "Local authority maintained schools",
    "detailed_type": "Voluntary aided school"
  }
]
